DSMVLib/DSMVLib.py
DSMVLib/__init__.py
DSMVLib-0.2.25.1.dist-info/LICENSE
DSMVLib-0.2.25.1.dist-info/METADATA
DSMVLib-0.2.25.1.dist-info/WHEEL
DSMVLib-0.2.25.1.dist-info/top_level.txt
DSMVLib-0.2.25.1.dist-info/RECORD
