Metadata-Version: 2.1
Name: DSMVLib
Version: 0.2.25.1
Summary: This is a library that simplifies command line output in C-style and provides a threaded serial port.
Home-page: https://github.com/pypa/sampleproject
Author: LukasFun
Author-email: lfreudenberg@uni-osnabrueck.de
Project-URL: Bug Tracker, https://github.com/pypa/sampleproject/issues
Classifier: Programming Language :: Python :: 3
Classifier: License :: OSI Approved :: MIT License
Classifier: Operating System :: OS Independent
Requires-Python: >=3.6
License-File: LICENSE
